bcelogger/__init__.py
bcelogger/base_logger.py
bcelogger/db_logger.py
bcelogger/default_logger.py
bcelogger/multi_logger.py
bcelogger/conf/__init__.py
bcelogger/conf/logit_conf.py
bcelogger/conf/logit_db_conf.py
bcelogger/conf/logit_multi_conf.py
bcelogger-1.2.0.7.dist-info/METADATA
bcelogger-1.2.0.7.dist-info/WHEEL
bcelogger-1.2.0.7.dist-info/top_level.txt
bcelogger-1.2.0.7.dist-info/RECORD
